{
  "blocks": [
    {
      "rect": [
        118.6704,
        0.0,
        433.3344,
        86.6669
      ],
      "targets": []
    },
    {
      "rect": [
        451.9968,
        249.3293,
        441.3312,
        42.6662
      ],
      "targets": []
    },
    {
      "rect": [
        -0.0048,
        211.9968,
        433.3344,
        117.3312
      ],
      "targets": []
    },
    {
      "rect": [
        110.664,
        378.0,
        484.0032,
        72.0
      ],
      "targets": []
    },
    {
      "rect": [
        613.9968,
        370.6666,
        549.3312,
        86.6669
      ],
      "targets": []
    },
    {
      "rect": [
        118.6704,
        128.0045,
        433.3344,
        42.6662
      ],
      "targets": []
    },
    {
      "rect": [
        404.0016,
        498.6624,
        433.3344,
        72.0
      ],
      "targets": []
    }
  ],
  "edges": [
    {
      "type": "UnconditionalBranch",
      "format": "bspline",
      "points": [
        335.3376,
        86.6966,
        335.3376,
        100.7808,
        335.3376,
        115.8432,
        335.3376,
        127.5264
      ]
    },
    {
      "type": "TrueBranch",
      "format": "bspline",
      "points": [
        627.1584,
        292.0032,
        576.432,
        314.304,
        493.4496,
        350.784,
        431.9904,
        377.7984
      ]
    },
    {
      "type": "FalseBranch",
      "format": "bspline",
      "points": [
        703.6128,
        292.1568,
        734.88,
        312.5088,
        784.1088,
        344.5824,
        823.9392,
        370.512
      ]
    },
    {
      "type": "UnconditionalBranch",
      "format": "bspline",
      "points": [
        301.7664,
        211.7664,
        305.1456,
        208.3872,
        308.352,
        204.912,
        311.3376,
        201.3312,
        318.816,
        192.3648,
        324.5568,
        180.672,
        328.5408,
        170.7744
      ]
    },
    {
      "type": "UnconditionalBranch",
      "format": "bspline",
      "points": [
        431.6256,
        450.096,
        466.368,
        465.3984,
        507.0816,
        483.3216,
        541.8048,
        498.6144
      ]
    },
    {
      "type": "UnconditionalBranch",
      "format": "bspline",
      "points": [
        793.0464,
        457.4304,
        762.384,
        470.9376,
        728.784,
        485.7312,
        699.4656,
        498.6432
      ]
    },
    {
      "type": "TrueBranch",
      "format": "bspline",
      "points": [
        453.12,
        170.7648,
        465.6864,
        173.8752,
        478.1856,
        177.3888,
        490.0032,
        181.3344,
        543.5904,
        199.2288,
        601.7856,
        229.2768,
        637.7472,
        249.2064
      ]
    },
    {
      "type": "FalseBranch",
      "format": "bspline",
      "points": [
        230.544,
        170.7552,
        222.9504,
        173.8752,
        217.0656,
        177.3888,
        214.0032,
        181.3344,
        207.2352,
        190.0128,
        204.4896,
        200.7744,
        204.0384,
        211.7568
      ]
    }
  ],
  "width": 1163.328,
  "height": 570.6624
}